mensajes/__init__.py
mensajes/adios/__init__.py
mensajes/adios/despedida.py
mensajes/hola/__init__.py
mensajes/hola/saludos.py
tests/__init__.py
tests/test_adios.py
tests/test_hola.py
Mensajes_LucasBoff-5.0.dist-info/LICENSE
Mensajes_LucasBoff-5.0.dist-info/METADATA
Mensajes_LucasBoff-5.0.dist-info/WHEEL
Mensajes_LucasBoff-5.0.dist-info/top_level.txt
Mensajes_LucasBoff-5.0.dist-info/RECORD
